rtl/sdf_feedback_delay.sv
// sdf_feedback_delay.sv
// Shift-register delay line with combinational output for SDF feedback paths.
//
// Unlike delay_line_shift (which has a registered output), this module
// provides a combinational read from sr[DELAY-1].  This avoids the
// one-clock skew at phase boundaries when placed in a feedback loop.
//
// Shifts only when en == 1.
// No valid/sync.  No RAM.  No circular buffer.

module sdf_feedback_delay #(
    parameter int DATA_W = 16,
    parameter int DELAY  = 4
)(
    input  logic                      clk,
    input  logic                      rst_n,
    input  logic                      en,
    input  logic signed [DATA_W-1:0]  din_re,
    input  logic signed [DATA_W-1:0]  din_im,
    output logic signed [DATA_W-1:0]  dout_re,
    output logic signed [DATA_W-1:0]  dout_im
);

    // Shift register: DELAY stages, combinational output
    logic signed [DATA_W-1:0] sr_re [0:DELAY-1];
    logic signed [DATA_W-1:0] sr_im [0:DELAY-1];

    assign dout_re = sr_re[DELAY-1];
    assign dout_im = sr_im[DELAY-1];

    integer i;

    always_ff @(posedge clk or negedge rst_n) begin
        if (!rst_n) begin
            for (i = 0; i < DELAY; i = i + 1) begin
                sr_re[i] <= '0;
                sr_im[i] <= '0;
            end
        end else if (en) begin
            sr_re[0] <= din_re;
            sr_im[0] <= din_im;
            for (i = 1; i < DELAY; i = i + 1) begin
                sr_re[i] <= sr_re[i-1];
                sr_im[i] <= sr_im[i-1];
            end
        end
    end

endmodule

rtl/trivial_rotator.sv
// trivial_rotator.sv
// Multiplier-free complex rotation by {1, -j, -1, j}.
// Pure combinational — no clock, no reset.

module trivial_rotator #(
    parameter int DATA_W = 16
)(
    input  logic [1:0]               rot_sel,
    input  logic signed [DATA_W-1:0] in_re,
    input  logic signed [DATA_W-1:0] in_im,
    output logic signed [DATA_W-1:0] out_re,
    output logic signed [DATA_W-1:0] out_im
);

    always_comb begin
        case (rot_sel)
            2'd0: begin  // * 1
                out_re =  in_re;
                out_im =  in_im;
            end
            2'd1: begin  // * (-j)
                out_re =  in_im;
                out_im = -in_re;
            end
            2'd2: begin  // * (-1)
                out_re = -in_re;
                out_im = -in_im;
            end
            2'd3: begin  // * j
                out_re = -in_im;
                out_im =  in_re;
            end
            default: begin
                out_re = in_re;
                out_im = in_im;
            end
        endcase
    end

endmodule

rtl/butterfly_radix2_scaled.sv
// butterfly_radix2_scaled.sv
// Scaled Radix-2 butterfly: y0 = (a+b)>>>1, y1 = (a-b)>>>1.
// Applied independently to real and imaginary parts.
// Pure combinational — no clock, no reset.
// Sign-extends inputs to DATA_W+1 before add/sub.
// Uses arithmetic right shift (>>>). No saturation.

module butterfly_radix2_scaled #(
    parameter int DATA_W = 16
)(
    input  logic signed [DATA_W-1:0] a_re, a_im,  // delayed sample
    input  logic signed [DATA_W-1:0] b_re, b_im,  // current sample
    output logic signed [DATA_W-1:0] y0_re, y0_im, // scaled sum
    output logic signed [DATA_W-1:0] y1_re, y1_im  // scaled difference
);

    // Extended-width intermediates
    logic signed [DATA_W:0] sum_re, sum_im, diff_re, diff_im;

    always_comb begin
        // Sign-extend and add/subtract
        sum_re  = {a_re[DATA_W-1], a_re} + {b_re[DATA_W-1], b_re};
        sum_im  = {a_im[DATA_W-1], a_im} + {b_im[DATA_W-1], b_im};
        diff_re = {a_re[DATA_W-1], a_re} - {b_re[DATA_W-1], b_re};
        diff_im = {a_im[DATA_W-1], a_im} - {b_im[DATA_W-1], b_im};

        // Arithmetic right shift by 1, then truncate to DATA_W
        y0_re = (sum_re  >>> 1);
        y0_im = (sum_im  >>> 1);
        y1_re = (diff_re >>> 1);
        y1_im = (diff_im >>> 1);
    end

endmodule

rtl/sdf_bf2ii_stage.sv
// sdf_bf2ii_stage.sv
// Radix-2² SDF BF2II stage.
// Similar to BF2I, but during fill phase (phase_sel=0) the output
// passes through trivial_rotator before being forwarded.
//
// Uses: butterfly_radix2_scaled, trivial_rotator, sdf_feedback_delay.
// No CMUL.  No internal counter.  phase_sel and rot_sel are external.
//
// Behavior:
//   phase_sel == 0 (fill):
//       delay_write_in = din
//       dout = trivial_rotator(delay_out, rot_sel)
//
//   phase_sel == 1 (compute):
//       a = delay_out, b = din
//       y0 = (a+b)>>>1,  y1 = (a-b)>>>1
//       delay_write_in = y1
//       dout = y0
//
// dout is combinational (no output register).
// valid_out / sync_out delayed by DELAY cycles (DELAY+1-stage SR,
// combinational output, same method as sdf_bf2i_stage).

module sdf_bf2ii_stage #(
    parameter int DATA_W = 16,
    parameter int DELAY  = 4
)(
    input  logic                      clk,
    input  logic                      rst_n,
    input  logic                      valid_in,
    input  logic                      sync_in,
    input  logic                      phase_sel,   // 0 = fill, 1 = compute
    input  logic [1:0]                rot_sel,     // trivial rotation selector
    input  logic signed [DATA_W-1:0]  din_re,
    input  logic signed [DATA_W-1:0]  din_im,
    output logic                      valid_out,
    output logic                      sync_out,
    output logic signed [DATA_W-1:0]  dout_re,
    output logic signed [DATA_W-1:0]  dout_im
);

    // ----------------------------------------------------------------
    // Internal wires
    // ----------------------------------------------------------------
    logic signed [DATA_W-1:0] delay_in_re,  delay_in_im;
    logic signed [DATA_W-1:0] delay_out_re, delay_out_im;
    logic signed [DATA_W-1:0] y0_re, y0_im, y1_re, y1_im;
    logic signed [DATA_W-1:0] rot_out_re, rot_out_im;

    // ----------------------------------------------------------------
    // Butterfly — purely combinational
    // a = delay_out (stored sample), b = din (current input)
    // ----------------------------------------------------------------
    butterfly_radix2_scaled #(.DATA_W(DATA_W)) u_bf (
        .a_re  (delay_out_re),
        .a_im  (delay_out_im),
        .b_re  (din_re),
        .b_im  (din_im),
        .y0_re (y0_re),
        .y0_im (y0_im),
        .y1_re (y1_re),
        .y1_im (y1_im)
    );

    // ----------------------------------------------------------------
    // Trivial rotator — purely combinational
    // Applied to delay_out during fill phase (phase_sel=0).
    // ----------------------------------------------------------------
    trivial_rotator #(.DATA_W(DATA_W)) u_rot (
        .rot_sel (rot_sel),
        .in_re   (delay_out_re),
        .in_im   (delay_out_im),
        .out_re  (rot_out_re),
        .out_im  (rot_out_im)
    );

    // ----------------------------------------------------------------
    // Feedback mux — selects what is written into the delay SR
    //   fill    (phase_sel=0): store incoming sample
    //   compute (phase_sel=1): store butterfly difference y1
    // ----------------------------------------------------------------
    assign delay_in_re = phase_sel ? y1_re : din_re;
    assign delay_in_im = phase_sel ? y1_im : din_im;

    // ----------------------------------------------------------------
    // Output mux — combinational, no output register
    //   fill    (phase_sel=0): rotated delay output
    //   compute (phase_sel=1): butterfly sum y0
    // ----------------------------------------------------------------
    assign dout_re = phase_sel ? y0_re : rot_out_re;
    assign dout_im = phase_sel ? y0_im : rot_out_im;

    // ----------------------------------------------------------------
    // Feedback delay — sdf_feedback_delay (combinational output)
    // ----------------------------------------------------------------
    sdf_feedback_delay #(
        .DATA_W (DATA_W),
        .DELAY  (DELAY)
    ) u_fbdelay (
        .clk    (clk),
        .rst_n  (rst_n),
        .en     (1'b1),
        .din_re (delay_in_re),
        .din_im (delay_in_im),
        .dout_re(delay_out_re),
        .dout_im(delay_out_im)
    );

    // ----------------------------------------------------------------
    // Valid / sync shift register — DELAY+1 depth, combinational output
    // Same method as sdf_bf2i_stage.
    // ----------------------------------------------------------------
    logic [DELAY-1:0] v_sr;
    logic [DELAY-1:0] s_sr;

    assign valid_out = v_sr[DELAY-1];
    assign sync_out  = s_sr[DELAY-1];

    always_ff @(posedge clk or negedge rst_n) begin
        if (!rst_n) begin
            v_sr <= '0;
            s_sr <= '0;
        end else begin
            v_sr <= {v_sr[DELAY-1:0], valid_in};
            s_sr <= {s_sr[DELAY-1:0], sync_in};
        end
    end

endmodule

sim/tb_sdf_bf2ii_stage.sv
// tb_sdf_bf2ii_stage.sv
// Self-checking testbench for sdf_bf2ii_stage with DELAY = 4.
// Drives din_re = 10*(n+1), din_im = 5*(n+1).
// Tests all 4 rot_sel values during fill phase cycles 8-11.
// Compares cycle-by-cycle against the manual timing table.
// Generates VCD.  Prints PASS only if all checks pass.

`timescale 1ns/1ps

module tb_sdf_bf2ii_stage;

    localparam int DATA_W     = 16;
    localparam int DELAY      = 4;
    localparam int NUM_CYCLES = 16;

    // DUT signals
    logic                      clk, rst_n;
    logic                      valid_in, sync_in, phase_sel;
    logic [1:0]                rot_sel;
    logic signed [DATA_W-1:0]  din_re, din_im;
    logic                      valid_out, sync_out;
    logic signed [DATA_W-1:0]  dout_re, dout_im;

    sdf_bf2ii_stage #(.DATA_W(DATA_W), .DELAY(DELAY)) dut (.*);

    // Clock — 10 ns period
    initial clk = 0;
    always #5 clk = ~clk;

    // ------------------------------------------------------------------
    // Expected values from the manual timing table
    //
    // din_re = 10*(c+1), din_im = 5*(c+1)
    // rot_sel: fill phases use {0,1,2,3}, compute phases use 0
    //
    // Rotator applied during fill (phase_sel=0) on delay_out:
    //   rot=0: (re, im)     rot=1: (im, -re)
    //   rot=2: (-re, -im)   rot=3: (-im, re)
    //
    // Cycles 0-3: fill, delay_out=(0,0), dout=(0,0) regardless of rot
    // Cycles 4-7: compute, dout=y0
    // Cycles 8-11: fill, delay_out=(-20,-10), rotated output
    // Cycles 12-15: compute, dout=y0
    // ------------------------------------------------------------------

    logic signed [DATA_W-1:0] exp_re [0:NUM_CYCLES-1];
    logic signed [DATA_W-1:0] exp_im [0:NUM_CYCLES-1];
    logic                     exp_v  [0:NUM_CYCLES-1];
    logic                     exp_s  [0:NUM_CYCLES-1];

    // phase_sel pattern: 0 for cnt[2]==0, 1 for cnt[2]==1
    logic [2:0] tb_cnt;

    // rot_sel pattern per cycle
    logic [1:0] rot_pattern [0:NUM_CYCLES-1];

    initial begin
        // rot_sel: fill phases cycle through 0,1,2,3; compute phases = 0
        rot_pattern[ 0] = 0; rot_pattern[ 1] = 1;
        rot_pattern[ 2] = 2; rot_pattern[ 3] = 3;
        rot_pattern[ 4] = 0; rot_pattern[ 5] = 0;
        rot_pattern[ 6] = 0; rot_pattern[ 7] = 0;
        rot_pattern[ 8] = 0; rot_pattern[ 9] = 1;
        rot_pattern[10] = 2; rot_pattern[11] = 3;
        rot_pattern[12] = 0; rot_pattern[13] = 0;
        rot_pattern[14] = 0; rot_pattern[15] = 0;

        // Expected dout_re
        exp_re[ 0] =   0;  exp_im[ 0] =   0;   // fill, delay_out=0, rot=0
        exp_re[ 1] =   0;  exp_im[ 1] =   0;   // fill, delay_out=0, rot=1
        exp_re[ 2] =   0;  exp_im[ 2] =   0;   // fill, delay_out=0, rot=2
        exp_re[ 3] =   0;  exp_im[ 3] =   0;   // fill, delay_out=0, rot=3
        exp_re[ 4] =  30;  exp_im[ 4] =  15;   // compute: y0=(10+50)/2, (5+25)/2
        exp_re[ 5] =  40;  exp_im[ 5] =  20;   // compute: y0=(20+60)/2, (10+30)/2
        exp_re[ 6] =  50;  exp_im[ 6] =  25;   // compute: y0=(30+70)/2, (15+35)/2
        exp_re[ 7] =  60;  exp_im[ 7] =  30;   // compute: y0=(40+80)/2, (20+40)/2
        exp_re[ 8] = -20;  exp_im[ 8] = -10;   // fill, dly=(-20,-10), unrotated
        exp_re[ 9] = -20;  exp_im[ 9] = -10;   // fill, dly=(-20,-10), unrotated
        exp_re[10] = -20;  exp_im[10] = -10;   // fill, dly=(-20,-10), unrotated
        exp_re[11] = -20;  exp_im[11] = -10;   // fill, dly=(-20,-10), unrotated
        exp_re[12] = 110;  exp_im[12] =  55;   // compute: y0=(90+130)/2, (45+65)/2
        exp_re[13] = 120;  exp_im[13] =  60;   // compute: y0=(100+140)/2, (50+70)/2
        exp_re[14] = 130;  exp_im[14] =  65;   // compute: y0=(110+150)/2, (55+75)/2
        exp_re[15] = 140;  exp_im[15] =  70;   // compute: y0=(120+160)/2, (60+80)/2

        // valid_out / sync_out
        for (int k = 0; k < NUM_CYCLES; k++) begin
            exp_v[k] = (k >= DELAY) ? 1 : 0;
            exp_s[k] = (k == DELAY) ? 1 : 0;
        end
    end

    // VCD
    initial begin
        $dumpfile("tb_sdf_bf2ii_stage.vcd");
        $dumpvars(0, tb_sdf_bf2ii_stage);
    end

    // ------------------------------------------------------------------
    // Stimulus & checking
    // Timing: set inputs → #1 settle → check → @(posedge clk)
    // ------------------------------------------------------------------
    integer cycle, errors;

    initial begin
        rst_n = 0; valid_in = 0; sync_in = 0;
        phase_sel = 0; rot_sel = 0;
        din_re = 0; din_im = 0;
        tb_cnt = 0; errors = 0;

        repeat (3) @(posedge clk);
        rst_n = 1;
        @(posedge clk);

        for (cycle = 0; cycle < NUM_CYCLES; cycle = cycle + 1) begin
            // Set inputs
            valid_in  <= 1;
            sync_in   <= (cycle == 0) ? 1 : 0;
            din_re    <= 16'(10 * (cycle + 1));
            din_im    <= 16'( 5 * (cycle + 1));
            phase_sel <= tb_cnt[2];
            rot_sel   <= rot_pattern[cycle];

            #1;  // settle

            // Check
            if (dout_re !== exp_re[cycle]) begin
                $display("FAIL cyc %0d: dout_re=%0d exp=%0d", cycle, dout_re, exp_re[cycle]);
                errors = errors + 1;
            end
            if (dout_im !== exp_im[cycle]) begin
                $display("FAIL cyc %0d: dout_im=%0d exp=%0d", cycle, dout_im, exp_im[cycle]);
                errors = errors + 1;
            end
            if (valid_out !== exp_v[cycle]) begin
                $display("FAIL cyc %0d: valid_out=%0d exp=%0d", cycle, valid_out, exp_v[cycle]);
                errors = errors + 1;
            end
            if (sync_out !== exp_s[cycle]) begin
                $display("FAIL cyc %0d: sync_out=%0d exp=%0d", cycle, sync_out, exp_s[cycle]);
                errors = errors + 1;
            end

            $display("cyc %2d: ph=%0d rot=%0d din=(%4d,%4d) dout=(%4d,%4d) v=%0d s=%0d | exp=(%4d,%4d) v=%0d s=%0d %s",
                     cycle, phase_sel, rot_sel, din_re, din_im,
                     dout_re, dout_im, valid_out, sync_out,
                     exp_re[cycle], exp_im[cycle], exp_v[cycle], exp_s[cycle],
                     (dout_re===exp_re[cycle] && dout_im===exp_im[cycle] &&
                      valid_out===exp_v[cycle] && sync_out===exp_s[cycle]) ? "OK" : "MISMATCH");

            @(posedge clk);
            tb_cnt = tb_cnt + 1;
        end

        $display("");
        if (errors == 0)
            $display("=== PASS === All %0d cycle checks passed.", NUM_CYCLES);
        else
            $display("=== FAIL === %0d errors in %0d cycles.", errors, NUM_CYCLES);

        #20; $finish;
    end

endmodule

tb_sdf_bf2ii_stage.vcd
$date
	Wed May 27 11:05:24 2026
$end
$version
	Icarus Verilog
$end
$timescale
	1ps
$end
$scope module tb_sdf_bf2ii_stage $end
$var wire 1 ! valid_out $end
$var wire 1 " sync_out $end
$var wire 16 # dout_re [15:0] $end
$var wire 16 $ dout_im [15:0] $end
$var parameter 32 % DATA_W $end
$var parameter 32 & DELAY $end
$var parameter 32 ' NUM_CYCLES $end
$var reg 1 ( clk $end
$var reg 16 ) din_im [15:0] $end
$var reg 16 * din_re [15:0] $end
$var reg 1 + phase_sel $end
$var reg 2 , rot_sel [1:0] $end
$var reg 1 - rst_n $end
$var reg 1 . sync_in $end
$var reg 3 / tb_cnt [2:0] $end
$var reg 1 0 valid_in $end
$var integer 32 1 cycle [31:0] $end
$var integer 32 2 errors [31:0] $end
$scope module dut $end
$var wire 1 ( clk $end
$var wire 16 3 delay_out_im [15:0] $end
$var wire 16 4 delay_out_re [15:0] $end
$var wire 16 5 din_im [15:0] $end
$var wire 16 6 din_re [15:0] $end
$var wire 1 + phase_sel $end
$var wire 2 7 rot_sel [1:0] $end
$var wire 1 - rst_n $end
$var wire 1 . sync_in $end
$var wire 1 0 valid_in $end
$var wire 16 8 y1_re [15:0] $end
$var wire 16 9 y1_im [15:0] $end
$var wire 16 : y0_re [15:0] $end
$var wire 16 ; y0_im [15:0] $end
$var wire 1 ! valid_out $end
$var wire 1 " sync_out $end
$var wire 16 < rot_out_re [15:0] $end
$var wire 16 = rot_out_im [15:0] $end
$var wire 16 > dout_re [15:0] $end
$var wire 16 ? dout_im [15:0] $end
$var wire 16 @ delay_in_re [15:0] $end
$var wire 16 A delay_in_im [15:0] $end
$var parameter 32 B DATA_W $end
$var parameter 32 C DELAY $end
$var reg 4 D s_sr [3:0] $end
$var reg 4 E v_sr [3:0] $end
$scope module u_bf $end
$var wire 16 F a_im [15:0] $end
$var wire 16 G a_re [15:0] $end
$var wire 16 H b_re [15:0] $end
$var wire 16 I b_im [15:0] $end
$var parameter 32 J DATA_W $end
$var reg 17 K diff_im [16:0] $end
$var reg 17 L diff_re [16:0] $end
$var reg 17 M sum_im [16:0] $end
$var reg 17 N sum_re [16:0] $end
$var reg 16 O y0_im [15:0] $end
$var reg 16 P y0_re [15:0] $end
$var reg 16 Q y1_im [15:0] $end
$var reg 16 R y1_re [15:0] $end
$upscope $end
$scope module u_fbdelay $end
$var wire 1 ( clk $end
$var wire 16 S din_im [15:0] $end
$var wire 16 T din_re [15:0] $end
$var wire 16 U dout_im [15:0] $end
$var wire 16 V dout_re [15:0] $end
$var wire 1 W en $end
$var wire 1 - rst_n $end
$var parameter 32 X DATA_W $end
$var parameter 32 Y DELAY $end
$var integer 32 Z i [31:0] $end
$upscope $end
$scope module u_rot $end
$var wire 16 [ in_im [15:0] $end
$var wire 16 \ in_re [15:0] $end
$var wire 2 ] rot_sel [1:0] $end
$var parameter 32 ^ DATA_W $end
$var reg 16 _ out_im [15:0] $end
$var reg 16 ` out_re [15:0] $end
$upscope $end
$upscope $end
$scope begin $ivl_for_loop0 $end
$var integer 32 a k [31:0] $end
$upscope $end
$upscope $end
$enddefinitions $end
$comment Show the parameter values. $end
$dumpall
b10000 ^
b100 Y
b10000 X
b10000 J
b100 C
b10000 B
b10000 '
b100 &
b10000 %
$end
#0
$dumpvars
b10000 a
b0 `
b0 _
b0 ]
b0 \
b0 [
b100 Z
1W
b0 V
b0 U
b0 T
b0 S
b0 R
b0 Q
b0 P
b0 O
b0 N
b0 M
b0 L
b0 K
b0 I
b0 H
b0 G
b0 F
b0 E
b0 D
b0 A
b0 @
b0 ?
b0 >
b0 =
b0 <
b0 ;
b0 :
b0 9
b0 8
b0 7
b0 6
b0 5
b0 4
b0 3
b0 2
bx 1
00
b0 /
0.
0-
b0 ,
0+
b0 *
b0 )
0(
b0 $
b0 #
0"
0!
$end
#5000
b100 Z
1(
#10000
0(
#15000
b100 Z
1(
#20000
0(
#25000
b100 Z
1-
1(
#30000
0(
#35000
b1111111111111101 9
b1111111111111101 Q
b1111111111111011 8
b1111111111111011 R
b10 ;
b10 O
b101 :
b101 P
b11111111111111011 K
b11111111111110110 L
b101 M
b1010 N
b101 A
b101 S
b1010 @
b1010 T
b101 =
b101 I
b101 _
b1010 <
b1010 H
b1010 `
b101 )
b101 5
b101 [
b1010 *
b1010 6
b1010 \
1.
10
b100 Z
b0 1
1(
#40000
0(
#45000
b1010 9
b1010 Q
b1111111111110110 ;
b1111111111110110 O
b10100 K
b11111111111101100 M
b1010 A
b1010 S
b10100 @
b10100 T
b1111111111101100 =
b1111111111101100 I
b1111111111101100 _
b1 D
b1 E
b1 ,
b1 7
b1 ]
b1010 )
b1010 5
b1010 [
b10100 *
b10100 6
b10100 \
0.
b100 Z
b1 1
b1 /
1(
#50000
0(
#55000
b111 9
b111 Q
b1111 8
b1111 R
b1111111111111000 ;
b1111111111111000 O
b1111111111110001 :
b1111111111110001 P
b1111 K
b11110 L
b11111111111110001 M
b11111111111100010 N
b1111 A
b1111 S
b11110 @
b11110 T
b1111111111110001 =
b1111111111110001 I
b1111111111110001 _
b1111111111100010 <
b1111111111100010 H
b1111111111100010 `
b10 D
b11 E
b10 ,
b10 7
b10 ]
b1111 )
b1111 5
b1111 [
b11110 *
b11110 6
b11110 \
b100 Z
b10 1
b10 /
1(
#60000
0(
#65000
b1111111111101100 9
b1111111111101100 Q
b1010 8
b1010 R
b10100 ;
b10100 O
b1111111111110110 :
b1111111111110110 P
b11111111111011000 K
b10100 L
b101000 M
b11111111111101100 N
b10100 A
b10100 S
b101000 @
b101000 T
b101000 =
b101000 I
b101000 _
b1111111111101100 <
b1111111111101100 H
b1111111111101100 `
b100 D
b111 E
b11 ,
b11 7
b11 ]
b10100 )
b10100 5
b10100 [
b101000 *
b101000 6
b101000 \
b100 Z
b11 1
b11 /
1(
#70000
0(
#75000
b1111111111110110 9
b1111111111110110 Q
b1111111111101100 8
b1111111111101100 R
b1111 ;
b1111 O
b11110 :
b11110 P
b11111111111101100 K
b11111111111011000 L
b11110 M
b111100 N
1"
1!
b11110 #
b11110 >
b1111 $
b1111 ?
b1111111111110110 A
b1111111111110110 S
b1111111111101100 @
b1111111111101100 T
b11001 =
b11001 I
b11001 _
b110010 <
b110010 H
b110010 `
b101 3
b101 F
b101 U
b1010 4
b1010 G
b1010 V
b1000 D
b1111 E
b0 ,
b0 7
b0 ]
1+
b11001 )
b11001 5
b11001 [
b110010 *
b110010 6
b110010 \
b100 Z
b100 1
b100 /
1(
#80000
0(
#85000
b10100 $
b10100 ?
b101000 #
b101000 >
0"
b10100 ;
b10100 O
b101000 :
b101000 P
b101000 M
b1010000 N
b11110 =
b11110 I
b11110 _
b111100 <
b111100 H
b111100 `
b0 D
b1010 3
b1010 F
b1010 U
b10100 4
b10100 G
b10100 V
b11110 )
b11110 5
b11110 [
b111100 *
b111100 6
b111100 \
b100 Z
b101 1
b101 /
1(
#90000
0(
#95000
b11001 $
b11001 ?
b110010 #
b110010 >
b11001 ;
b11001 O
b110010 :
b110010 P
b110010 M
b1100100 N
b100011 =
b100011 I
b100011 _
b1000110 <
b1000110 H
b1000110 `
b1111 3
b1111 F
b1111 U
b11110 4
b11110 G
b11110 V
b100011 )
b100011 5
b100011 [
b1000110 *
b1000110 6
b1000110 \
b100 Z
b110 1
b110 /
1(
#100000
0(
#105000
b11110 $
b11110 ?
b111100 #
b111100 >
b11110 ;
b11110 O
b111100 :
b111100 P
b111100 M
b1111000 N
b101000 =
b101000 I
b101000 _
b1010000 <
b1010000 H
b1010000 `
b10100 3
b10100 F
b10100 U
b101000 4
b101000 G
b101000 V
b101000 )
b101000 5
b101000 [
b1010000 *
b1010000 6
b1010000 \
b100 Z
b111 1
b111 /
1(
#110000
0(
#115000
b1111111111100100 9
b1111111111100100 Q
b1111111111001001 8
b1111111111001001 R
b10001 ;
b10001 O
b100011 :
b100011 P
b11111111111001001 K
b11111111110010010 L
b100011 M
b1000110 N
b1011010 @
b1011010 T
b101101 A
b101101 S
b1111111111101100 #
b1111111111101100 >
b1111111111110110 $
b1111111111110110 ?
b101101 =
b101101 I
b101101 _
b1011010 <
b1011010 H
b1011010 `
b1111111111110110 3
b1111111111110110 F
b1111111111110110 U
b1111111111101100 4
b1111111111101100 G
b1111111111101100 V
0+
b101101 )
b101101 5
b101101 [
b1011010 *
b1011010 6
b1011010 \
b100 Z
b1000 1
b0 /
1(
#120000
0(
#125000
b101101 9
b101101 Q
b1111111111011101 8
b1111111111011101 R
b1111111111001001 ;
b1111111111001001 O
b1111 :
b1111 P
b1011010 K
b11111111110111010 L
b11111111110010010 M
b11110 N
b110010 A
b110010 S
b1100100 @
b1100100 T
b1111111110011100 =
b1111111110011100 I
b1111111110011100 _
b110010 <
b110010 H
b110010 `
b1 ,
b1 7
b1 ]
b110010 )
b110010 5
b110010 [
b1100100 *
b1100100 6
b1100100 \
b100 Z
b1001 1
b1 /
1(
#130000
0(
#135000
b10110 9
b10110 Q
b101101 8
b101101 R
b1111111111011111 ;
b1111111111011111 O
b1111111110111111 :
b1111111110111111 P
b101101 K
b1011010 L
b11111111110111111 M
b11111111101111110 N
b110111 A
b110111 S
b1101110 @
b1101110 T
b1111111111001001 =
b1111111111001001 I
b1111111111001001 _
b1111111110010010 <
b1111111110010010 H
b1111111110010010 `
b10 ,
b10 7
b10 ]
b110111 )
b110111 5
b110111 [
b1101110 *
b1101110 6
b1101110 \
b100 Z
b1010 1
b10 /
1(
#140000
0(
#145000
b1111111110111111 9
b1111111110111111 Q
b10100 8
b10100 R
b110111 ;
b110111 O
b1111111111011000 :
b1111111111011000 P
b11111111101111110 K
b101000 L
b1101110 M
b11111111110110000 N
b111100 A
b111100 S
b1111000 @
b1111000 T
b1111000 =
b1111000 I
b1111000 _
b1111111111000100 <
b1111111111000100 H
b1111111111000100 `
b11 ,
b11 7
b11 ]
b111100 )
b111100 5
b111100 [
b1111000 *
b1111000 6
b1111000 \
b100 Z
b1011 1
b11 /
1(
#150000
0(
#155000
b1111111111110110 9
b1111111111110110 Q
b1111111111101100 8
b1111111111101100 R
b1101110 :
b1101110 P
b11111111111101100 K
b11111111111011000 L
b11011100 N
b1101110 #
b1101110 >
b110111 $
b110111 ?
b1111111111110110 A
b1111111111110110 S
b1111111111101100 @
b1111111111101100 T
b1000001 =
b1000001 I
b1000001 _
b10000010 <
b10000010 H
b10000010 `
b101101 3
b101101 F
b101101 U
b1011010 4
b1011010 G
b1011010 V
b0 ,
b0 7
b0 ]
1+
b1000001 )
b1000001 5
b1000001 [
b10000010 *
b10000010 6
b10000010 \
b100 Z
b1100 1
b100 /
1(
#160000
0(
#165000
b111100 $
b111100 ?
b1111000 #
b1111000 >
b111100 ;
b111100 O
b1111000 :
b1111000 P
b1111000 M
b11110000 N
b1000110 =
b1000110 I
b1000110 _
b10001100 <
b10001100 H
b10001100 `
b110010 3
b110010 F
b110010 U
b1100100 4
b1100100 G
b1100100 V
b1000110 )
b1000110 5
b1000110 [
b10001100 *
b10001100 6
b10001100 \
b100 Z
b1101 1
b101 /
1(
#170000
0(
#175000
b1000001 $
b1000001 ?
b10000010 #
b10000010 >
b1000001 ;
b1000001 O
b10000010 :
b10000010 P
b10000010 M
b100000100 N
b1001011 =
b1001011 I
b1001011 _
b10010110 <
b10010110 H
b10010110 `
b110111 3
b110111 F
b110111 U
b1101110 4
b1101110 G
b1101110 V
b1001011 )
b1001011 5
b1001011 [
b10010110 *
b10010110 6
b10010110 \
b100 Z
b1110 1
b110 /
1(
#180000
0(
#185000
b1000110 $
b1000110 ?
b10001100 #
b10001100 >
b1000110 ;
b1000110 O
b10001100 :
b10001100 P
b10001100 M
b100011000 N
b1010000 =
b1010000 I
b1010000 _
b10100000 <
b10100000 H
b10100000 `
b111100 3
b111100 F
b111100 U
b1111000 4
b1111000 G
b1111000 V
b1010000 )
b1010000 5
b1010000 [
b10100000 *
b10100000 6
b10100000 \
b100 Z
b1111 1
b111 /
1(
#190000
0(
#195000
b1111111111010011 A
b1111111111010011 S
b1111111110100110 @
b1111111110100110 T
b100011 $
b100011 ?
b1000110 #
b1000110 >
b1111111111010011 9
b1111111111010011 Q
b1111111110100110 8
b1111111110100110 R
b100011 ;
b100011 O
b1000110 :
b1000110 P
b11111111110100110 K
b11111111101001100 L
b1000110 M
b10001100 N
b1111111111110110 3
b1111111111110110 F
b1111111111110110 U
b1111111111101100 4
b1111111111101100 G
b1111111111101100 V
b100 Z
b10000 1
b0 /
1(
#200000
0(
#205000
b100 Z
1(
#210000
0(
#215000
b100 Z
1(
