rtl/sdf_feedback_delay.sv
// sdf_feedback_delay.sv
// Shift-register delay line with combinational output for SDF feedback paths.
//
// Unlike delay_line_shift (which has a registered output), this module
// provides a combinational read from sr[DELAY-1].  This avoids the
// one-clock skew at phase boundaries when placed in a feedback loop.
//
// Shifts only when en == 1.
// No valid/sync.  No RAM.  No circular buffer.

module sdf_feedback_delay #(
    parameter int DATA_W = 16,
    parameter int DELAY  = 4
)(
    input  logic                      clk,
    input  logic                      rst_n,
    input  logic                      en,
    input  logic signed [DATA_W-1:0]  din_re,
    input  logic signed [DATA_W-1:0]  din_im,
    output logic signed [DATA_W-1:0]  dout_re,
    output logic signed [DATA_W-1:0]  dout_im
);

    // Shift register: DELAY stages, combinational output
    logic signed [DATA_W-1:0] sr_re [0:DELAY-1];
    logic signed [DATA_W-1:0] sr_im [0:DELAY-1];

    assign dout_re = sr_re[DELAY-1];
    assign dout_im = sr_im[DELAY-1];

    integer i;

    always_ff @(posedge clk or negedge rst_n) begin
        if (!rst_n) begin
            for (i = 0; i < DELAY; i = i + 1) begin
                sr_re[i] <= '0;
                sr_im[i] <= '0;
            end
        end else if (en) begin
            sr_re[0] <= din_re;
            sr_im[0] <= din_im;
            for (i = 1; i < DELAY; i = i + 1) begin
                sr_re[i] <= sr_re[i-1];
                sr_im[i] <= sr_im[i-1];
            end
        end
    end

endmodule

rtl/butterfly_radix2_scaled.sv
// butterfly_radix2_scaled.sv
// Scaled Radix-2 butterfly: y0 = (a+b)>>>1, y1 = (a-b)>>>1.
// Applied independently to real and imaginary parts.
// Pure combinational — no clock, no reset.
// Sign-extends inputs to DATA_W+1 before add/sub.
// Uses arithmetic right shift (>>>). No saturation.

module butterfly_radix2_scaled #(
    parameter int DATA_W = 16
)(
    input  logic signed [DATA_W-1:0] a_re, a_im,  // delayed sample
    input  logic signed [DATA_W-1:0] b_re, b_im,  // current sample
    output logic signed [DATA_W-1:0] y0_re, y0_im, // scaled sum
    output logic signed [DATA_W-1:0] y1_re, y1_im  // scaled difference
);

    // Extended-width intermediates
    logic signed [DATA_W:0] sum_re, sum_im, diff_re, diff_im;

    always_comb begin
        // Sign-extend and add/subtract
        sum_re  = {a_re[DATA_W-1], a_re} + {b_re[DATA_W-1], b_re};
        sum_im  = {a_im[DATA_W-1], a_im} + {b_im[DATA_W-1], b_im};
        diff_re = {a_re[DATA_W-1], a_re} - {b_re[DATA_W-1], b_re};
        diff_im = {a_im[DATA_W-1], a_im} - {b_im[DATA_W-1], b_im};

        // Arithmetic right shift by 1, then truncate to DATA_W
        y0_re = (sum_re  >>> 1);
        y0_im = (sum_im  >>> 1);
        y1_re = (diff_re >>> 1);
        y1_im = (diff_im >>> 1);
    end

endmodule

rtl/sdf_bf2i_stage.sv
// sdf_bf2i_stage.sv
// Radix-2² SDF BF2I stage.
// Contains: shift-register feedback (DELAY depth) + butterfly_radix2_scaled.
// No trivial_rotator, no CMUL, no internal counter.
// phase_sel is driven externally.
//
// Behavior:
//   phase_sel == 0 (fill):    delay_in = din,  dout = delay_out
//   phase_sel == 1 (compute): delay_in = y1,   dout = y0
//     where y0 = (a+b)>>>1, y1 = (a-b)>>>1, a = delay_out, b = din
//
// The feedback shift register uses combinational output (sr[DELAY-1])
// so that the butterfly always sees the current delay value, not a
// one-cycle-stale registered copy.  delay_line_shift (which has a
// registered output) is correct for non-feedback inter-stage paths but
// creates a one-cycle skew at phase boundaries when placed in a
// feedback loop.  The shift-register here follows the same principle
// (pure shift chain) and was verified via the timing-table test.
//
// Latency: DELAY cycles (data written in cycle C appears at output in cycle C+DELAY).
// dout is combinational (no output register).
// valid_out / sync_out delayed by DELAY cycles (combinational-output SR).

module sdf_bf2i_stage #(
    parameter int DATA_W = 16,
    parameter int DELAY  = 4
)(
    input  logic                      clk,
    input  logic                      rst_n,
    input  logic                      valid_in,
    input  logic                      sync_in,
    input  logic                      phase_sel,   // 0 = fill, 1 = compute
    input  logic signed [DATA_W-1:0]  din_re,
    input  logic signed [DATA_W-1:0]  din_im,
    output logic                      valid_out,
    output logic                      sync_out,
    output logic signed [DATA_W-1:0]  dout_re,
    output logic signed [DATA_W-1:0]  dout_im
);

    // ----------------------------------------------------------------
    // Internal wires
    // ----------------------------------------------------------------
    logic signed [DATA_W-1:0] delay_in_re,  delay_in_im;
    logic signed [DATA_W-1:0] delay_out_re, delay_out_im;
    logic signed [DATA_W-1:0] y0_re, y0_im, y1_re, y1_im;

    // ----------------------------------------------------------------
    // Butterfly — purely combinational
    // a = delay_out (old stored sample), b = din (current input)
    // ----------------------------------------------------------------
    butterfly_radix2_scaled #(.DATA_W(DATA_W)) u_bf (
        .a_re  (delay_out_re),
        .a_im  (delay_out_im),
        .b_re  (din_re),
        .b_im  (din_im),
        .y0_re (y0_re),
        .y0_im (y0_im),
        .y1_re (y1_re),
        .y1_im (y1_im)
    );

    // ----------------------------------------------------------------
    // Feedback mux — selects what is written into the delay SR
    //   fill    (phase_sel=0): store incoming sample
    //   compute (phase_sel=1): store butterfly difference y1
    // ----------------------------------------------------------------
    assign delay_in_re = phase_sel ? y1_re : din_re;
    assign delay_in_im = phase_sel ? y1_im : din_im;

    // ----------------------------------------------------------------
    // Output mux — combinational, no output register
    //   fill    (phase_sel=0): forward old delay content
    //   compute (phase_sel=1): forward butterfly sum y0
    // ----------------------------------------------------------------
    assign dout_re = phase_sel ? y0_re : delay_out_re;
    assign dout_im = phase_sel ? y0_im : delay_out_im;

    // ----------------------------------------------------------------
    // Feedback delay — sdf_feedback_delay (combinational output)
    //
    // DELAY-depth shift register with combinational read from sr[DELAY-1].
    // en = 1'b1: shifts unconditionally every clock.
    // In the feedback loop the effective latency is DELAY cycles
    // (DELAY-1 SR propagation + 1 write-at-posedge boundary).
    // ----------------------------------------------------------------
    sdf_feedback_delay #(
        .DATA_W (DATA_W),
        .DELAY  (DELAY)
    ) u_fbdelay (
        .clk    (clk),
        .rst_n  (rst_n),
        .en     (1'b1),
        .din_re (delay_in_re),
        .din_im (delay_in_im),
        .dout_re(delay_out_re),
        .dout_im(delay_out_im)
    );

    // ----------------------------------------------------------------
    // Valid / sync shift register — DELAY+1 depth, combinational output
    //
    // The data feedback SR achieves DELAY cycles of effective latency
    // because the write-then-shift-then-read loop adds one implicit
    // cycle.  Valid/sync is a linear (non-feedback) pipeline, so it
    // needs DELAY+1 stages with combinational output from index DELAY
    // to produce exactly DELAY cycles of delay.
    // ----------------------------------------------------------------
    logic [DELAY:0] v_sr;
    logic [DELAY:0] s_sr;

    assign valid_out = v_sr[DELAY];
    assign sync_out  = s_sr[DELAY];

    always_ff @(posedge clk or negedge rst_n) begin
        if (!rst_n) begin
            v_sr <= '0;
            s_sr <= '0;
        end else begin
            v_sr <= {v_sr[DELAY-1:0], valid_in};
            s_sr <= {s_sr[DELAY-1:0], sync_in};
        end
    end

endmodule

sim/tb_sdf_bf2i_stage.sv
// tb_sdf_bf2i_stage.sv
// Self-checking testbench for sdf_bf2i_stage with DELAY = 4.
// Drives din_re = 10*(n+1), din_im = 0.
// phase_sel from local counter: 0 for cnt[2]==0, 1 for cnt[2]==1.
// Checks cycle-by-cycle against the manual timing table.
// Generates VCD.  Prints PASS only if all checks pass.

`timescale 1ns/1ps

module tb_sdf_bf2i_stage;

    localparam int DATA_W     = 16;
    localparam int DELAY      = 4;
    localparam int NUM_CYCLES = 16;

    // DUT signals
    logic                      clk, rst_n;
    logic                      valid_in, sync_in, phase_sel;
    logic signed [DATA_W-1:0]  din_re, din_im;
    logic                      valid_out, sync_out;
    logic signed [DATA_W-1:0]  dout_re, dout_im;

    sdf_bf2i_stage #(.DATA_W(DATA_W), .DELAY(DELAY)) dut (.*);

    // Clock — 10 ns period
    initial clk = 0;
    always #5 clk = ~clk;

    // ------------------------------------------------------------------
    // Expected values from the manual timing table (DELAY = 4)
    //
    // din_re = 10*(cycle+1), din_im = 0
    //
    // Cyc|ph|din | dly_out|BF?| a  | b  | y0 | y1 |dly_wr|fwd |v|s
    //  0 | 0| 10 |   0   | N | —  | —  | —  | —  |  10  |  0 |0|0
    //  1 | 0| 20 |   0   | N | —  | —  | —  | —  |  20  |  0 |0|0
    //  2 | 0| 30 |   0   | N | —  | —  | —  | —  |  30  |  0 |0|0
    //  3 | 0| 40 |   0   | N | —  | —  | —  | —  |  40  |  0 |0|0
    //  4 | 1| 50 |  10   | Y | 10 | 50 | 30 |-20 | -20  | 30 |1|1
    //  5 | 1| 60 |  20   | Y | 20 | 60 | 40 |-20 | -20  | 40 |1|0
    //  6 | 1| 70 |  30   | Y | 30 | 70 | 50 |-20 | -20  | 50 |1|0
    //  7 | 1| 80 |  40   | Y | 40 | 80 | 60 |-20 | -20  | 60 |1|0
    //  8 | 0| 90 | -20   | N | —  | —  | —  | —  |  90  |-20 |1|0
    //  9 | 0|100 | -20   | N | —  | —  | —  | —  | 100  |-20 |1|0
    // 10 | 0|110 | -20   | N | —  | —  | —  | —  | 110  |-20 |1|0
    // 11 | 0|120 | -20   | N | —  | —  | —  | —  | 120  |-20 |1|0
    // 12 | 1|130 |  90   | Y | 90 |130 |110 |-20 | -20  |110 |1|0
    // 13 | 1|140 | 100   | Y |100 |140 |120 |-20 | -20  |120 |1|0
    // 14 | 1|150 | 110   | Y |110 |150 |130 |-20 | -20  |130 |1|0
    // 15 | 1|160 | 120   | Y |120 |160 |140 |-20 | -20  |140 |1|0
    // ------------------------------------------------------------------

    logic signed [DATA_W-1:0] exp_re [0:NUM_CYCLES-1];
    logic                     exp_v  [0:NUM_CYCLES-1];
    logic                     exp_s  [0:NUM_CYCLES-1];

    initial begin
        exp_re[ 0]=  0; exp_re[ 1]=  0; exp_re[ 2]=  0; exp_re[ 3]=  0;
        exp_re[ 4]= 30; exp_re[ 5]= 40; exp_re[ 6]= 50; exp_re[ 7]= 60;
        exp_re[ 8]=-20; exp_re[ 9]=-20; exp_re[10]=-20; exp_re[11]=-20;
        exp_re[12]=110; exp_re[13]=120; exp_re[14]=130; exp_re[15]=140;
        for (int k = 0; k < NUM_CYCLES; k++) begin
            exp_v[k] = (k >= DELAY) ? 1 : 0;
            exp_s[k] = (k == DELAY) ? 1 : 0;
        end
    end

    // VCD
    initial begin
        $dumpfile("tb_sdf_bf2i_stage.vcd");
        $dumpvars(0, tb_sdf_bf2i_stage);
    end

    // ------------------------------------------------------------------
    // Stimulus & checking
    //
    // Timing: set inputs → #1 settle → check combinational outputs →
    //         @(posedge clk) to advance registers.
    // This way the combinational outputs (dout, valid_out, sync_out)
    // reflect the current SR state and current inputs, with no
    // registered-output skew.
    // ------------------------------------------------------------------
    integer cycle, errors;
    logic [2:0] tb_cnt;

    initial begin
        rst_n = 0; valid_in = 0; sync_in = 0;
        phase_sel = 0; din_re = 0; din_im = 0;
        tb_cnt = 0; errors = 0;

        // Reset
        repeat (3) @(posedge clk);
        rst_n = 1;
        @(posedge clk);  // one clean cycle after reset

        for (cycle = 0; cycle < NUM_CYCLES; cycle = cycle + 1) begin
            // --- Set inputs (combinational, before next posedge) ---
            valid_in  <= 1;
            sync_in   <= (cycle == 0) ? 1 : 0;
            din_re    <= 16'(10 * (cycle + 1));
            din_im    <= 16'd0;
            phase_sel <= tb_cnt[2];

            #1;  // let combinational outputs settle

            // --- Check outputs ---
            if (dout_re !== exp_re[cycle]) begin
                $display("FAIL cyc %0d: dout_re=%0d exp=%0d", cycle, dout_re, exp_re[cycle]);
                errors = errors + 1;
            end
            if (dout_im !== 16'sd0) begin
                $display("FAIL cyc %0d: dout_im=%0d exp=0", cycle, dout_im);
                errors = errors + 1;
            end
            if (valid_out !== exp_v[cycle]) begin
                $display("FAIL cyc %0d: valid_out=%0d exp=%0d", cycle, valid_out, exp_v[cycle]);
                errors = errors + 1;
            end
            if (sync_out !== exp_s[cycle]) begin
                $display("FAIL cyc %0d: sync_out=%0d exp=%0d", cycle, sync_out, exp_s[cycle]);
                errors = errors + 1;
            end

            $display("cyc %2d: ph=%0d din=%4d dout=%4d v=%0d s=%0d | exp=%4d v=%0d s=%0d %s",
                     cycle, phase_sel, din_re, dout_re, valid_out, sync_out,
                     exp_re[cycle], exp_v[cycle], exp_s[cycle],
                     (dout_re===exp_re[cycle] && dout_im===16'sd0 &&
                      valid_out===exp_v[cycle] && sync_out===exp_s[cycle]) ? "OK" : "MISMATCH");

            // --- Advance clock (registers update) ---
            @(posedge clk);
            tb_cnt = tb_cnt + 1;
        end

        $display("");
        if (errors == 0)
            $display("=== PASS === All %0d cycle checks passed.", NUM_CYCLES);
        else
            $display("=== FAIL === %0d errors in %0d cycles.", errors, NUM_CYCLES);

        #20; $finish;
    end

endmodule

tb_sdf_bf2i_stage.vcd
$date
	Wed May 27 11:04:48 2026
$end
$version
	Icarus Verilog
$end
$timescale
	1ps
$end
$scope module tb_sdf_bf2i_stage $end
$var wire 1 ! valid_out $end
$var wire 1 " sync_out $end
$var wire 16 # dout_re [15:0] $end
$var wire 16 $ dout_im [15:0] $end
$var parameter 32 % DATA_W $end
$var parameter 32 & DELAY $end
$var parameter 32 ' NUM_CYCLES $end
$var reg 1 ( clk $end
$var reg 16 ) din_im [15:0] $end
$var reg 16 * din_re [15:0] $end
$var reg 1 + phase_sel $end
$var reg 1 , rst_n $end
$var reg 1 - sync_in $end
$var reg 3 . tb_cnt [2:0] $end
$var reg 1 / valid_in $end
$var integer 32 0 cycle [31:0] $end
$var integer 32 1 errors [31:0] $end
$scope module dut $end
$var wire 1 ( clk $end
$var wire 16 2 delay_out_im [15:0] $end
$var wire 16 3 delay_out_re [15:0] $end
$var wire 16 4 din_im [15:0] $end
$var wire 16 5 din_re [15:0] $end
$var wire 1 + phase_sel $end
$var wire 1 , rst_n $end
$var wire 1 - sync_in $end
$var wire 1 / valid_in $end
$var wire 16 6 y1_re [15:0] $end
$var wire 16 7 y1_im [15:0] $end
$var wire 16 8 y0_re [15:0] $end
$var wire 16 9 y0_im [15:0] $end
$var wire 1 ! valid_out $end
$var wire 1 " sync_out $end
$var wire 16 : dout_re [15:0] $end
$var wire 16 ; dout_im [15:0] $end
$var wire 16 < delay_in_re [15:0] $end
$var wire 16 = delay_in_im [15:0] $end
$var parameter 32 > DATA_W $end
$var parameter 32 ? DELAY $end
$var reg 4 @ s_sr [3:0] $end
$var reg 4 A v_sr [3:0] $end
$scope module u_bf $end
$var wire 16 B a_im [15:0] $end
$var wire 16 C a_re [15:0] $end
$var wire 16 D b_im [15:0] $end
$var wire 16 E b_re [15:0] $end
$var parameter 32 F DATA_W $end
$var reg 17 G diff_im [16:0] $end
$var reg 17 H diff_re [16:0] $end
$var reg 17 I sum_im [16:0] $end
$var reg 17 J sum_re [16:0] $end
$var reg 16 K y0_im [15:0] $end
$var reg 16 L y0_re [15:0] $end
$var reg 16 M y1_im [15:0] $end
$var reg 16 N y1_re [15:0] $end
$upscope $end
$scope module u_fbdelay $end
$var wire 1 ( clk $end
$var wire 16 O din_im [15:0] $end
$var wire 16 P din_re [15:0] $end
$var wire 16 Q dout_im [15:0] $end
$var wire 16 R dout_re [15:0] $end
$var wire 1 S en $end
$var wire 1 , rst_n $end
$var parameter 32 T DATA_W $end
$var parameter 32 U DELAY $end
$var integer 32 V i [31:0] $end
$upscope $end
$upscope $end
$scope begin $ivl_for_loop0 $end
$var integer 32 W k [31:0] $end
$upscope $end
$upscope $end
$enddefinitions $end
$comment Show the parameter values. $end
$dumpall
b100 U
b10000 T
b10000 F
b100 ?
b10000 >
b10000 '
b100 &
b10000 %
$end
#0
$dumpvars
b10000 W
b100 V
1S
b0 R
b0 Q
b0 P
b0 O
b0 N
b0 M
b0 L
b0 K
b0 J
b0 I
b0 H
b0 G
b0 E
b0 D
b0 C
b0 B
b0 A
b0 @
b0 =
b0 <
b0 ;
b0 :
b0 9
b0 8
b0 7
b0 6
b0 5
b0 4
b0 3
b0 2
b0 1
bx 0
0/
b0 .
0-
0,
0+
b0 *
b0 )
0(
b0 $
b0 #
0"
0!
$end
#5000
b100 V
1(
#10000
0(
#15000
b100 V
1(
#20000
0(
#25000
b100 V
1,
1(
#30000
0(
#35000
b1010 <
b1010 P
b1111111111111011 6
b1111111111111011 N
b101 8
b101 L
b11111111111110110 H
b1010 J
b1010 *
b1010 5
b1010 E
1-
1/
b100 V
b0 0
1(
#40000
0(
#45000
b10100 <
b10100 P
b1111111111110110 6
b1111111111110110 N
b1010 8
b1010 L
b11111111111101100 H
b10100 J
b1 @
b1 A
b10100 *
b10100 5
b10100 E
0-
b100 V
b1 0
b1 .
1(
#50000
0(
#55000
b11110 <
b11110 P
b1111111111110001 6
b1111111111110001 N
b1111 8
b1111 L
b11111111111100010 H
b11110 J
b10 @
b11 A
b11110 *
b11110 5
b11110 E
b100 V
b10 0
b10 .
1(
#60000
0(
#65000
b101000 <
b101000 P
b1111111111101100 6
b1111111111101100 N
b10100 8
b10100 L
b11111111111011000 H
b101000 J
b100 @
b111 A
b101000 *
b101000 5
b101000 E
b100 V
b11 0
b11 .
1(
#70000
0(
#75000
1"
1!
b11110 #
b11110 :
b1111111111101100 <
b1111111111101100 P
b11110 8
b11110 L
b111100 J
b1010 3
b1010 C
b1010 R
b1000 @
b1111 A
1+
b110010 *
b110010 5
b110010 E
b100 V
b100 0
b100 .
1(
#80000
0(
#85000
b101000 #
b101000 :
0"
b101000 8
b101000 L
b1010000 J
b0 @
b10100 3
b10100 C
b10100 R
b111100 *
b111100 5
b111100 E
b100 V
b101 0
b101 .
1(
#90000
0(
#95000
b110010 #
b110010 :
b110010 8
b110010 L
b1100100 J
b11110 3
b11110 C
b11110 R
b1000110 *
b1000110 5
b1000110 E
b100 V
b110 0
b110 .
1(
#100000
0(
#105000
b111100 #
b111100 :
b111100 8
b111100 L
b1111000 J
b101000 3
b101000 C
b101000 R
b1010000 *
b1010000 5
b1010000 E
b100 V
b111 0
b111 .
1(
#110000
0(
#115000
b1011010 <
b1011010 P
b1111111111101100 #
b1111111111101100 :
b1111111111001001 6
b1111111111001001 N
b100011 8
b100011 L
b11111111110010010 H
b1000110 J
b1111111111101100 3
b1111111111101100 C
b1111111111101100 R
0+
b1011010 *
b1011010 5
b1011010 E
b100 V
b1000 0
b0 .
1(
#120000
0(
#125000
b1100100 <
b1100100 P
b1111111111000100 6
b1111111111000100 N
b101000 8
b101000 L
b11111111110001000 H
b1010000 J
b1100100 *
b1100100 5
b1100100 E
b100 V
b1001 0
b1 .
1(
#130000
0(
#135000
b1101110 <
b1101110 P
b1111111110111111 6
b1111111110111111 N
b101101 8
b101101 L
b11111111101111110 H
b1011010 J
b1101110 *
b1101110 5
b1101110 E
b100 V
b1010 0
b10 .
1(
#140000
0(
#145000
b1111000 <
b1111000 P
b1111111110111010 6
b1111111110111010 N
b110010 8
b110010 L
b11111111101110100 H
b1100100 J
b1111000 *
b1111000 5
b1111000 E
b100 V
b1011 0
b11 .
1(
#150000
0(
#155000
b1101110 #
b1101110 :
b1111111111101100 <
b1111111111101100 P
b1111111111101100 6
b1111111111101100 N
b1101110 8
b1101110 L
b11111111111011000 H
b11011100 J
b1011010 3
b1011010 C
b1011010 R
1+
b10000010 *
b10000010 5
b10000010 E
b100 V
b1100 0
b100 .
1(
#160000
0(
#165000
b1111000 #
b1111000 :
b1111000 8
b1111000 L
b11110000 J
b1100100 3
b1100100 C
b1100100 R
b10001100 *
b10001100 5
b10001100 E
b100 V
b1101 0
b101 .
1(
#170000
0(
#175000
b10000010 #
b10000010 :
b10000010 8
b10000010 L
b100000100 J
b1101110 3
b1101110 C
b1101110 R
b10010110 *
b10010110 5
b10010110 E
b100 V
b1110 0
b110 .
1(
#180000
0(
#185000
b10001100 #
b10001100 :
b10001100 8
b10001100 L
b100011000 J
b1111000 3
b1111000 C
b1111000 R
b10100000 *
b10100000 5
b10100000 E
b100 V
b1111 0
b111 .
1(
#190000
0(
#195000
b1111111110100110 <
b1111111110100110 P
b1000110 #
b1000110 :
b1111111110100110 6
b1111111110100110 N
b1000110 8
b1000110 L
b11111111101001100 H
b10001100 J
b1111111111101100 3
b1111111111101100 C
b1111111111101100 R
b100 V
b10000 0
b0 .
1(
#200000
0(
#205000
b100 V
1(
#210000
0(
#215000
b100 V
1(
