rtl/sdf_feedback_delay.sv
// sdf_feedback_delay.sv
// Shift-register delay line with combinational output for SDF feedback paths.
//
// Unlike delay_line_shift (which has a registered output), this module
// provides a combinational read from sr[DELAY-1].  This avoids the
// one-clock skew at phase boundaries when placed in a feedback loop.
//
// Shifts only when en == 1.
// No valid/sync.  No RAM.  No circular buffer.

module sdf_feedback_delay #(
    parameter int DATA_W = 16,
    parameter int DELAY  = 4
)(
    input  logic                      clk,
    input  logic                      rst_n,
    input  logic                      en,
    input  logic signed [DATA_W-1:0]  din_re,
    input  logic signed [DATA_W-1:0]  din_im,
    output logic signed [DATA_W-1:0]  dout_re,
    output logic signed [DATA_W-1:0]  dout_im
);

    // Shift register: DELAY stages, combinational output
    logic signed [DATA_W-1:0] sr_re [0:DELAY-1];
    logic signed [DATA_W-1:0] sr_im [0:DELAY-1];

    assign dout_re = sr_re[DELAY-1];
    assign dout_im = sr_im[DELAY-1];

    integer i;

    always_ff @(posedge clk or negedge rst_n) begin
        if (!rst_n) begin
            for (i = 0; i < DELAY; i = i + 1) begin
                sr_re[i] <= '0;
                sr_im[i] <= '0;
            end
        end else if (en) begin
            sr_re[0] <= din_re;
            sr_im[0] <= din_im;
            for (i = 1; i < DELAY; i = i + 1) begin
                sr_re[i] <= sr_re[i-1];
                sr_im[i] <= sr_im[i-1];
            end
        end
    end

endmodule

sim/tb_sdf_feedback_delay.sv
// tb_sdf_feedback_delay.sv
// Self-checking testbench for sdf_feedback_delay.
// Tests DELAY = 1, 2, 4, 8.
// Prints PASS only if all checks pass.

`timescale 1ns/1ps

module tb_sdf_feedback_delay;

    localparam int DATA_W = 16;
    localparam int MAX_CYC = 20; // enough for DELAY=8 + extra

    logic clk;
    initial clk = 0;
    always #5 clk = ~clk;

    logic rst_n;
    integer total_errors;

    // ----------------------------------------------------------------
    // DUT instances
    // ----------------------------------------------------------------
    logic en1, en2, en4, en8;
    logic signed [DATA_W-1:0] d1i_re, d1i_im, d1o_re, d1o_im;
    logic signed [DATA_W-1:0] d2i_re, d2i_im, d2o_re, d2o_im;
    logic signed [DATA_W-1:0] d4i_re, d4i_im, d4o_re, d4o_im;
    logic signed [DATA_W-1:0] d8i_re, d8i_im, d8o_re, d8o_im;

    sdf_feedback_delay #(.DATA_W(DATA_W), .DELAY(1)) u1 (
        .clk(clk),.rst_n(rst_n),.en(en1),
        .din_re(d1i_re),.din_im(d1i_im),.dout_re(d1o_re),.dout_im(d1o_im));
    sdf_feedback_delay #(.DATA_W(DATA_W), .DELAY(2)) u2 (
        .clk(clk),.rst_n(rst_n),.en(en2),
        .din_re(d2i_re),.din_im(d2i_im),.dout_re(d2o_re),.dout_im(d2o_im));
    sdf_feedback_delay #(.DATA_W(DATA_W), .DELAY(4)) u4 (
        .clk(clk),.rst_n(rst_n),.en(en4),
        .din_re(d4i_re),.din_im(d4i_im),.dout_re(d4o_re),.dout_im(d4o_im));
    sdf_feedback_delay #(.DATA_W(DATA_W), .DELAY(8)) u8 (
        .clk(clk),.rst_n(rst_n),.en(en8),
        .din_re(d8i_re),.din_im(d8i_im),.dout_re(d8o_re),.dout_im(d8o_im));

    // VCD
    initial begin
        $dumpfile("tb_sdf_feedback_delay.vcd");
        $dumpvars(0, tb_sdf_feedback_delay);
    end

    // ----------------------------------------------------------------
    // Helper: expected output for cycle c with DELAY = D.
    //
    // With D SR stages and combinational output, the standalone latency
    // in this timing model (set inputs → #1 → check → posedge) is
    // D-1 clock cycles.  Data set during cycle c is latched at posedge,
    // propagates through D-1 more posedges, and appears at sr[D-1]
    // starting from cycle c + D - 1.
    //
    // In the SDF feedback loop the effective delay is D cycles because
    // the combinational write-to-read path adds the Dth cycle.
    //
    // Input at cycle c:  re = 10*(c+1),  im = -(5*(c+1)).
    // Standalone output at cycle c: input from cycle c-(D-1), or 0 if
    // c < D-1.
    // ----------------------------------------------------------------
    function automatic logic signed [DATA_W-1:0] exp_re(input int c, input int D);
        int eff;
        eff = D - 1;  // standalone latency
        if (c < eff) return 16'sd0;
        else         return 16'(10 * (c - eff + 1));
    endfunction

    function automatic logic signed [DATA_W-1:0] exp_im(input int c, input int D);
        int eff;
        eff = D - 1;
        if (c < eff) return 16'sd0;
        else         return 16'(-(5 * (c - eff + 1)));
    endfunction

    // ----------------------------------------------------------------
    // Main test
    // ----------------------------------------------------------------
    integer c, errs;
    logic signed [DATA_W-1:0] hold_re, hold_im;

    initial begin
        rst_n = 0;
        en1=0; en2=0; en4=0; en8=0;
        d1i_re=0; d1i_im=0; d2i_re=0; d2i_im=0;
        d4i_re=0; d4i_im=0; d8i_re=0; d8i_im=0;
        total_errors = 0;

        repeat (3) @(posedge clk);
        rst_n = 1;
        @(posedge clk);

        // ============================================================
        // Test DELAY = 1
        // ============================================================
        $display("--- DELAY=1 ---");
        errs = 0;
        for (c = 0; c < 10; c = c + 1) begin
            en1 = 1;
            d1i_re = 16'(10 * (c + 1));
            d1i_im = 16'(-(5 * (c + 1)));
            #1;
            if (d1o_re !== exp_re(c,1) || d1o_im !== exp_im(c,1)) begin
                $display("  FAIL D=1 c=%0d: got(%0d,%0d) exp(%0d,%0d)",
                    c, d1o_re, d1o_im, exp_re(c,1), exp_im(c,1));
                errs = errs + 1;
            end
            @(posedge clk);
        end
        // en=0 hold test
        en1 = 0; d1i_re = 16'h7FFF; d1i_im = 16'h7FFF;
        #1; hold_re = d1o_re; hold_im = d1o_im; @(posedge clk);
        en1 = 0; #1;
        if (d1o_re !== hold_re || d1o_im !== hold_im) begin
            $display("  FAIL D=1 en=0 hold"); errs = errs + 1;
        end
        @(posedge clk);
        total_errors = total_errors + errs;
        if (errs == 0) $display("  DELAY=1: passed.");
        else           $display("  DELAY=1: %0d errors.", errs);

        // ============================================================
        // Test DELAY = 2
        // ============================================================
        $display("--- DELAY=2 ---");
        errs = 0;
        for (c = 0; c < 12; c = c + 1) begin
            en2 = 1;
            d2i_re = 16'(10 * (c + 1));
            d2i_im = 16'(-(5 * (c + 1)));
            #1;
            if (d2o_re !== exp_re(c,2) || d2o_im !== exp_im(c,2)) begin
                $display("  FAIL D=2 c=%0d: got(%0d,%0d) exp(%0d,%0d)",
                    c, d2o_re, d2o_im, exp_re(c,2), exp_im(c,2));
                errs = errs + 1;
            end
            @(posedge clk);
        end
        en2 = 0; d2i_re = 16'h7FFF; d2i_im = 16'h7FFF;
        #1; hold_re = d2o_re; hold_im = d2o_im; @(posedge clk);
        en2 = 0; #1;
        if (d2o_re !== hold_re || d2o_im !== hold_im) begin
            $display("  FAIL D=2 en=0 hold"); errs = errs + 1;
        end
        @(posedge clk);
        total_errors = total_errors + errs;
        if (errs == 0) $display("  DELAY=2: passed.");
        else           $display("  DELAY=2: %0d errors.", errs);

        // ============================================================
        // Test DELAY = 4
        // ============================================================
        $display("--- DELAY=4 ---");
        errs = 0;
        for (c = 0; c < 14; c = c + 1) begin
            en4 = 1;
            d4i_re = 16'(10 * (c + 1));
            d4i_im = 16'(-(5 * (c + 1)));
            #1;
            if (d4o_re !== exp_re(c,4) || d4o_im !== exp_im(c,4)) begin
                $display("  FAIL D=4 c=%0d: got(%0d,%0d) exp(%0d,%0d)",
                    c, d4o_re, d4o_im, exp_re(c,4), exp_im(c,4));
                errs = errs + 1;
            end
            @(posedge clk);
        end
        en4 = 0; d4i_re = 16'h7FFF; d4i_im = 16'h7FFF;
        #1; hold_re = d4o_re; hold_im = d4o_im; @(posedge clk);
        en4 = 0; #1;
        if (d4o_re !== hold_re || d4o_im !== hold_im) begin
            $display("  FAIL D=4 en=0 hold"); errs = errs + 1;
        end
        @(posedge clk);
        total_errors = total_errors + errs;
        if (errs == 0) $display("  DELAY=4: passed.");
        else           $display("  DELAY=4: %0d errors.", errs);

        // ============================================================
        // Test DELAY = 8
        // ============================================================
        $display("--- DELAY=8 ---");
        errs = 0;
        for (c = 0; c < MAX_CYC; c = c + 1) begin
            en8 = 1;
            d8i_re = 16'(10 * (c + 1));
            d8i_im = 16'(-(5 * (c + 1)));
            #1;
            if (d8o_re !== exp_re(c,8) || d8o_im !== exp_im(c,8)) begin
                $display("  FAIL D=8 c=%0d: got(%0d,%0d) exp(%0d,%0d)",
                    c, d8o_re, d8o_im, exp_re(c,8), exp_im(c,8));
                errs = errs + 1;
            end
            @(posedge clk);
        end
        en8 = 0; d8i_re = 16'h7FFF; d8i_im = 16'h7FFF;
        #1; hold_re = d8o_re; hold_im = d8o_im; @(posedge clk);
        en8 = 0; #1;
        if (d8o_re !== hold_re || d8o_im !== hold_im) begin
            $display("  FAIL D=8 en=0 hold"); errs = errs + 1;
        end
        @(posedge clk);
        total_errors = total_errors + errs;
        if (errs == 0) $display("  DELAY=8: passed.");
        else           $display("  DELAY=8: %0d errors.", errs);

        // ============================================================
        // Final
        // ============================================================
        $display("");
        if (total_errors == 0)
            $display("=== PASS === All sdf_feedback_delay tests passed.");
        else
            $display("=== FAIL === %0d total errors.", total_errors);

        #20; $finish;
    end

endmodule

tb_sdf_feedback_delay.vcd
$date
	Wed May 27 11:04:49 2026
$end
$version
	Icarus Verilog
$end
$timescale
	1ps
$end
$scope module tb_sdf_feedback_delay $end
$var wire 16 ! d8o_re [15:0] $end
$var wire 16 " d8o_im [15:0] $end
$var wire 16 # d4o_re [15:0] $end
$var wire 16 $ d4o_im [15:0] $end
$var wire 16 % d2o_re [15:0] $end
$var wire 16 & d2o_im [15:0] $end
$var wire 16 ' d1o_re [15:0] $end
$var wire 16 ( d1o_im [15:0] $end
$var parameter 32 ) DATA_W $end
$var parameter 32 * MAX_CYC $end
$var reg 1 + clk $end
$var reg 16 , d1i_im [15:0] $end
$var reg 16 - d1i_re [15:0] $end
$var reg 16 . d2i_im [15:0] $end
$var reg 16 / d2i_re [15:0] $end
$var reg 16 0 d4i_im [15:0] $end
$var reg 16 1 d4i_re [15:0] $end
$var reg 16 2 d8i_im [15:0] $end
$var reg 16 3 d8i_re [15:0] $end
$var reg 1 4 en1 $end
$var reg 1 5 en2 $end
$var reg 1 6 en4 $end
$var reg 1 7 en8 $end
$var reg 16 8 hold_im [15:0] $end
$var reg 16 9 hold_re [15:0] $end
$var reg 1 : rst_n $end
$var integer 32 ; c [31:0] $end
$var integer 32 < errs [31:0] $end
$var integer 32 = total_errors [31:0] $end
$scope function exp_im $end
$upscope $end
$scope function exp_re $end
$upscope $end
$scope module u1 $end
$var wire 1 + clk $end
$var wire 16 > din_im [15:0] $end
$var wire 16 ? din_re [15:0] $end
$var wire 16 @ dout_im [15:0] $end
$var wire 16 A dout_re [15:0] $end
$var wire 1 4 en $end
$var wire 1 : rst_n $end
$var parameter 32 B DATA_W $end
$var parameter 32 C DELAY $end
$var integer 32 D i [31:0] $end
$upscope $end
$scope module u2 $end
$var wire 1 + clk $end
$var wire 16 E din_im [15:0] $end
$var wire 16 F din_re [15:0] $end
$var wire 16 G dout_im [15:0] $end
$var wire 16 H dout_re [15:0] $end
$var wire 1 5 en $end
$var wire 1 : rst_n $end
$var parameter 32 I DATA_W $end
$var parameter 32 J DELAY $end
$var integer 32 K i [31:0] $end
$upscope $end
$scope module u4 $end
$var wire 1 + clk $end
$var wire 16 L din_im [15:0] $end
$var wire 16 M din_re [15:0] $end
$var wire 16 N dout_im [15:0] $end
$var wire 16 O dout_re [15:0] $end
$var wire 1 6 en $end
$var wire 1 : rst_n $end
$var parameter 32 P DATA_W $end
$var parameter 32 Q DELAY $end
$var integer 32 R i [31:0] $end
$upscope $end
$scope module u8 $end
$var wire 1 + clk $end
$var wire 16 S din_im [15:0] $end
$var wire 16 T din_re [15:0] $end
$var wire 16 U dout_im [15:0] $end
$var wire 16 V dout_re [15:0] $end
$var wire 1 7 en $end
$var wire 1 : rst_n $end
$var parameter 32 W DATA_W $end
$var parameter 32 X DELAY $end
$var integer 32 Y i [31:0] $end
$upscope $end
$upscope $end
$enddefinitions $end
$comment Show the parameter values. $end
$dumpall
b1000 X
b10000 W
b100 Q
b10000 P
b10 J
b10000 I
b1 C
b10000 B
b10100 *
b10000 )
$end
#0
$dumpvars
b1000 Y
b0 V
b0 U
b0 T
b0 S
b100 R
b0 O
b0 N
b0 M
b0 L
b10 K
b0 H
b0 G
b0 F
b0 E
b1 D
b0 A
b0 @
b0 ?
b0 >
b0 =
bx <
bx ;
0:
bx 9
bx 8
07
06
05
04
b0 3
b0 2
b0 1
b0 0
b0 /
b0 .
b0 -
b0 ,
0+
b0 (
b0 '
b0 &
b0 %
b0 $
b0 #
b0 "
b0 !
$end
#5000
b1000 Y
b100 R
b10 K
b1 D
1+
#10000
0+
#15000
b1 D
b10 K
b100 R
b1000 Y
1+
#20000
0+
#25000
1:
1+
#30000
0+
#35000
b1111111111111011 (
b1111111111111011 @
b1010 '
b1010 A
b1111111111111011 ,
b1111111111111011 >
b1010 -
b1010 ?
14
b0 ;
b0 <
1+
#40000
0+
#45000
b1111111111110110 (
b1111111111110110 @
b10100 '
b10100 A
b1111111111110110 ,
b1111111111110110 >
b10100 -
b10100 ?
b1 ;
1+
#50000
0+
#55000
b1111111111110001 (
b1111111111110001 @
b11110 '
b11110 A
b1111111111110001 ,
b1111111111110001 >
b11110 -
b11110 ?
b10 ;
1+
#60000
0+
#65000
b1111111111101100 (
b1111111111101100 @
b101000 '
b101000 A
b1111111111101100 ,
b1111111111101100 >
b101000 -
b101000 ?
b11 ;
1+
#70000
0+
#75000
b1111111111100111 (
b1111111111100111 @
b110010 '
b110010 A
b1111111111100111 ,
b1111111111100111 >
b110010 -
b110010 ?
b100 ;
1+
#80000
0+
#85000
b1111111111100010 (
b1111111111100010 @
b111100 '
b111100 A
b1111111111100010 ,
b1111111111100010 >
b111100 -
b111100 ?
b101 ;
1+
#90000
0+
#95000
b1111111111011101 (
b1111111111011101 @
b1000110 '
b1000110 A
b1111111111011101 ,
b1111111111011101 >
b1000110 -
b1000110 ?
b110 ;
1+
#100000
0+
#105000
b1111111111011000 (
b1111111111011000 @
b1010000 '
b1010000 A
b1111111111011000 ,
b1111111111011000 >
b1010000 -
b1010000 ?
b111 ;
1+
#110000
0+
#115000
b1111111111010011 (
b1111111111010011 @
b1011010 '
b1011010 A
b1111111111010011 ,
b1111111111010011 >
b1011010 -
b1011010 ?
b1000 ;
1+
#120000
0+
#125000
b1111111111001110 (
b1111111111001110 @
b1100100 '
b1100100 A
b1111111111001110 ,
b1111111111001110 >
b1100100 -
b1100100 ?
b1001 ;
1+
#130000
0+
#135000
b111111111111111 ,
b111111111111111 >
b111111111111111 -
b111111111111111 ?
04
b1010 ;
1+
#136000
b1111111111001110 8
b1100100 9
#140000
0+
#145000
1+
#150000
0+
#155000
b10 K
b1111111111111011 .
b1111111111111011 E
b1010 /
b1010 F
15
b0 ;
1+
#160000
0+
#165000
b1111111111111011 &
b1111111111111011 G
b1010 %
b1010 H
b10 K
b1111111111110110 .
b1111111111110110 E
b10100 /
b10100 F
b1 ;
1+
#170000
0+
#175000
b1111111111110110 &
b1111111111110110 G
b10100 %
b10100 H
b10 K
b1111111111110001 .
b1111111111110001 E
b11110 /
b11110 F
b10 ;
1+
#180000
0+
#185000
b1111111111110001 &
b1111111111110001 G
b11110 %
b11110 H
b10 K
b1111111111101100 .
b1111111111101100 E
b101000 /
b101000 F
b11 ;
1+
#190000
0+
#195000
b1111111111101100 &
b1111111111101100 G
b101000 %
b101000 H
b10 K
b1111111111100111 .
b1111111111100111 E
b110010 /
b110010 F
b100 ;
1+
#200000
0+
#205000
b1111111111100111 &
b1111111111100111 G
b110010 %
b110010 H
b10 K
b1111111111100010 .
b1111111111100010 E
b111100 /
b111100 F
b101 ;
1+
#210000
0+
#215000
b1111111111100010 &
b1111111111100010 G
b111100 %
b111100 H
b10 K
b1111111111011101 .
b1111111111011101 E
b1000110 /
b1000110 F
b110 ;
1+
#220000
0+
#225000
b1111111111011101 &
b1111111111011101 G
b1000110 %
b1000110 H
b10 K
b1111111111011000 .
b1111111111011000 E
b1010000 /
b1010000 F
b111 ;
1+
#230000
0+
#235000
b1111111111011000 &
b1111111111011000 G
b1010000 %
b1010000 H
b10 K
b1111111111010011 .
b1111111111010011 E
b1011010 /
b1011010 F
b1000 ;
1+
#240000
0+
#245000
b1111111111010011 &
b1111111111010011 G
b1011010 %
b1011010 H
b10 K
b1111111111001110 .
b1111111111001110 E
b1100100 /
b1100100 F
b1001 ;
1+
#250000
0+
#255000
b1111111111001110 &
b1111111111001110 G
b1100100 %
b1100100 H
b10 K
b1111111111001001 .
b1111111111001001 E
b1101110 /
b1101110 F
b1010 ;
1+
#260000
0+
#265000
b1111111111001001 &
b1111111111001001 G
b1101110 %
b1101110 H
b10 K
b1111111111000100 .
b1111111111000100 E
b1111000 /
b1111000 F
b1011 ;
1+
#270000
0+
#275000
b111111111111111 .
b111111111111111 E
b111111111111111 /
b111111111111111 F
05
b1100 ;
1+
#276000
b1111111111001001 8
b1101110 9
#280000
0+
#285000
1+
#290000
0+
#295000
b100 R
b1111111111111011 0
b1111111111111011 L
b1010 1
b1010 M
16
b0 ;
1+
#300000
0+
#305000
b100 R
b1111111111110110 0
b1111111111110110 L
b10100 1
b10100 M
b1 ;
1+
#310000
0+
#315000
b100 R
b1111111111110001 0
b1111111111110001 L
b11110 1
b11110 M
b10 ;
1+
#320000
0+
#325000
b1111111111111011 $
b1111111111111011 N
b1010 #
b1010 O
b100 R
b1111111111101100 0
b1111111111101100 L
b101000 1
b101000 M
b11 ;
1+
#330000
0+
#335000
b1111111111110110 $
b1111111111110110 N
b10100 #
b10100 O
b100 R
b1111111111100111 0
b1111111111100111 L
b110010 1
b110010 M
b100 ;
1+
#340000
0+
#345000
b1111111111110001 $
b1111111111110001 N
b11110 #
b11110 O
b100 R
b1111111111100010 0
b1111111111100010 L
b111100 1
b111100 M
b101 ;
1+
#350000
0+
#355000
b1111111111101100 $
b1111111111101100 N
b101000 #
b101000 O
b100 R
b1111111111011101 0
b1111111111011101 L
b1000110 1
b1000110 M
b110 ;
1+
#360000
0+
#365000
b1111111111100111 $
b1111111111100111 N
b110010 #
b110010 O
b100 R
b1111111111011000 0
b1111111111011000 L
b1010000 1
b1010000 M
b111 ;
1+
#370000
0+
#375000
b1111111111100010 $
b1111111111100010 N
b111100 #
b111100 O
b100 R
b1111111111010011 0
b1111111111010011 L
b1011010 1
b1011010 M
b1000 ;
1+
#380000
0+
#385000
b1111111111011101 $
b1111111111011101 N
b1000110 #
b1000110 O
b100 R
b1111111111001110 0
b1111111111001110 L
b1100100 1
b1100100 M
b1001 ;
1+
#390000
0+
#395000
b1111111111011000 $
b1111111111011000 N
b1010000 #
b1010000 O
b100 R
b1111111111001001 0
b1111111111001001 L
b1101110 1
b1101110 M
b1010 ;
1+
#400000
0+
#405000
b1111111111010011 $
b1111111111010011 N
b1011010 #
b1011010 O
b100 R
b1111111111000100 0
b1111111111000100 L
b1111000 1
b1111000 M
b1011 ;
1+
#410000
0+
#415000
b1111111111001110 $
b1111111111001110 N
b1100100 #
b1100100 O
b100 R
b1111111110111111 0
b1111111110111111 L
b10000010 1
b10000010 M
b1100 ;
1+
#420000
0+
#425000
b1111111111001001 $
b1111111111001001 N
b1101110 #
b1101110 O
b100 R
b1111111110111010 0
b1111111110111010 L
b10001100 1
b10001100 M
b1101 ;
1+
#430000
0+
#435000
b111111111111111 0
b111111111111111 L
b111111111111111 1
b111111111111111 M
06
b1110 ;
1+
#440000
0+
#445000
1+
#450000
0+
#455000
b1000 Y
b1111111111111011 2
b1111111111111011 S
b1010 3
b1010 T
17
b0 ;
1+
#460000
0+
#465000
b1000 Y
b1111111111110110 2
b1111111111110110 S
b10100 3
b10100 T
b1 ;
1+
#470000
0+
#475000
b1000 Y
b1111111111110001 2
b1111111111110001 S
b11110 3
b11110 T
b10 ;
1+
#480000
0+
#485000
b1000 Y
b1111111111101100 2
b1111111111101100 S
b101000 3
b101000 T
b11 ;
1+
#490000
0+
#495000
b1000 Y
b1111111111100111 2
b1111111111100111 S
b110010 3
b110010 T
b100 ;
1+
#500000
0+
#505000
b1000 Y
b1111111111100010 2
b1111111111100010 S
b111100 3
b111100 T
b101 ;
1+
#510000
0+
#515000
b1000 Y
b1111111111011101 2
b1111111111011101 S
b1000110 3
b1000110 T
b110 ;
1+
#520000
0+
#525000
b1111111111111011 "
b1111111111111011 U
b1010 !
b1010 V
b1000 Y
b1111111111011000 2
b1111111111011000 S
b1010000 3
b1010000 T
b111 ;
1+
#530000
0+
#535000
b1111111111110110 "
b1111111111110110 U
b10100 !
b10100 V
b1000 Y
b1111111111010011 2
b1111111111010011 S
b1011010 3
b1011010 T
b1000 ;
1+
#540000
0+
#545000
b1111111111110001 "
b1111111111110001 U
b11110 !
b11110 V
b1000 Y
b1111111111001110 2
b1111111111001110 S
b1100100 3
b1100100 T
b1001 ;
1+
#550000
0+
#555000
b1111111111101100 "
b1111111111101100 U
b101000 !
b101000 V
b1000 Y
b1111111111001001 2
b1111111111001001 S
b1101110 3
b1101110 T
b1010 ;
1+
#560000
0+
#565000
b1111111111100111 "
b1111111111100111 U
b110010 !
b110010 V
b1000 Y
b1111111111000100 2
b1111111111000100 S
b1111000 3
b1111000 T
b1011 ;
1+
#570000
0+
#575000
b1111111111100010 "
b1111111111100010 U
b111100 !
b111100 V
b1000 Y
b1111111110111111 2
b1111111110111111 S
b10000010 3
b10000010 T
b1100 ;
1+
#580000
0+
#585000
b1111111111011101 "
b1111111111011101 U
b1000110 !
b1000110 V
b1000 Y
b1111111110111010 2
b1111111110111010 S
b10001100 3
b10001100 T
b1101 ;
1+
#590000
0+
#595000
b1111111111011000 "
b1111111111011000 U
b1010000 !
b1010000 V
b1000 Y
b1111111110110101 2
b1111111110110101 S
b10010110 3
b10010110 T
b1110 ;
1+
#600000
0+
#605000
b1111111111010011 "
b1111111111010011 U
b1011010 !
b1011010 V
b1000 Y
b1111111110110000 2
b1111111110110000 S
b10100000 3
b10100000 T
b1111 ;
1+
#610000
0+
#615000
b1111111111001110 "
b1111111111001110 U
b1100100 !
b1100100 V
b1000 Y
b1111111110101011 2
b1111111110101011 S
b10101010 3
b10101010 T
b10000 ;
1+
#620000
0+
#625000
b1111111111001001 "
b1111111111001001 U
b1101110 !
b1101110 V
b1000 Y
b1111111110100110 2
b1111111110100110 S
b10110100 3
b10110100 T
b10001 ;
1+
#630000
0+
#635000
b1111111111000100 "
b1111111111000100 U
b1111000 !
b1111000 V
b1000 Y
b1111111110100001 2
b1111111110100001 S
b10111110 3
b10111110 T
b10010 ;
1+
#640000
0+
#645000
b1111111110111111 "
b1111111110111111 U
b10000010 !
b10000010 V
b1000 Y
b1111111110011100 2
b1111111110011100 S
b11001000 3
b11001000 T
b10011 ;
1+
#650000
0+
#655000
b111111111111111 2
b111111111111111 S
b111111111111111 3
b111111111111111 T
07
b10100 ;
1+
#656000
b1111111110111111 8
b10000010 9
